gtfsmerger/__init__.py
gtfsmerger/gtfs.py
gtfsmerger-0.1.6.dist-info/DESCRIPTION.rst
gtfsmerger-0.1.6.dist-info/METADATA
gtfsmerger-0.1.6.dist-info/RECORD
gtfsmerger-0.1.6.dist-info/WHEEL
gtfsmerger-0.1.6.dist-info/metadata.json
gtfsmerger-0.1.6.dist-info/top_level.txt
tests/__init__.py
tests/conftest.py
tests/test_gtfs.py
tests/test_gtfsmerger.py
