Metadata-Version: 2.0
Name: gtfsmerger
Version: 0.1.6
Summary: Merge multiple GTFS files into one
Home-page: https://github.com/door2door-io/gtfs-merger
Author: Door2Door GmbH
Author-email: chenghsun@door2door.io
License: MIT
Keywords: gtfsmerger
Platform: UNKNOWN
Classifier: Development Status :: 2 - Pre-Alpha
Classifier: Intended Audience :: Developers
Classifier: License :: OSI Approved :: MIT License
Classifier: Natural Language :: English
Classifier: Programming Language :: Python :: 3.5
Classifier: Programming Language :: Python :: 3.6
Requires-Dist: pandas
